boltz/__init__.py
boltz/main.py
boltz/data/__init__.py
boltz/data/const.py
boltz/data/mol.py
boltz/data/pad.py
boltz/data/types.py
boltz/data/crop/__init__.py
boltz/data/crop/affinity.py
boltz/data/crop/boltz.py
boltz/data/crop/cropper.py
boltz/data/feature/__init__.py
boltz/data/feature/featurizer.py
boltz/data/feature/featurizerv2.py
boltz/data/feature/symmetry.py
boltz/data/filter/__init__.py
boltz/data/filter/dynamic/__init__.py
boltz/data/filter/dynamic/date.py
boltz/data/filter/dynamic/filter.py
boltz/data/filter/dynamic/max_residues.py
boltz/data/filter/dynamic/resolution.py
boltz/data/filter/dynamic/size.py
boltz/data/filter/dynamic/subset.py
boltz/data/filter/static/__init__.py
boltz/data/filter/static/filter.py
boltz/data/filter/static/ligand.py
boltz/data/filter/static/polymer.py
boltz/data/module/__init__.py
boltz/data/module/inference.py
boltz/data/module/inferencev2.py
boltz/data/module/training.py
boltz/data/module/trainingv2.py
boltz/data/msa/__init__.py
boltz/data/msa/mmseqs2.py
boltz/data/parse/__init__.py
boltz/data/parse/a3m.py
boltz/data/parse/csv.py
boltz/data/parse/fasta.py
boltz/data/parse/mmcif.py
boltz/data/parse/mmcif_with_constraints.py
boltz/data/parse/schema.py
boltz/data/parse/yaml.py
boltz/data/sample/__init__.py
boltz/data/sample/cluster.py
boltz/data/sample/distillation.py
boltz/data/sample/random.py
boltz/data/sample/sampler.py
boltz/data/tokenize/__init__.py
boltz/data/tokenize/boltz.py
boltz/data/tokenize/boltz2.py
boltz/data/tokenize/tokenizer.py
boltz/data/write/__init__.py
boltz/data/write/mmcif.py
boltz/data/write/pdb.py
boltz/data/write/utils.py
boltz/data/write/writer.py
boltz/model/__init__.py
boltz/model/layers/__init__.py
boltz/model/layers/attention.py
boltz/model/layers/attentionv2.py
boltz/model/layers/confidence_utils.py
boltz/model/layers/dropout.py
boltz/model/layers/initialize.py
boltz/model/layers/outer_product_mean.py
boltz/model/layers/pair_averaging.py
boltz/model/layers/pairformer.py
boltz-2.2.0.dist-info/licenses/LICENSE
boltz-2.2.0.dist-info/METADATA
boltz-2.2.0.dist-info/WHEEL
boltz-2.2.0.dist-info/entry_points.txt
boltz-2.2.0.dist-info/top_level.txt
boltz-2.2.0.dist-info/RECORD
